rogvibe/__init__.py
rogvibe/__main__.py
rogvibe/app.py
rogvibe/config.py
rogvibe/constants.py
rogvibe/apps/__init__.py
rogvibe/apps/flip_card_app.py
rogvibe/apps/lottery_app.py
rogvibe/apps/slot_machine_app.py
rogvibe/models/__init__.py
rogvibe/models/messages.py
rogvibe/utils/__init__.py
rogvibe/utils/detector.py
rogvibe/utils/executor.py
rogvibe/widgets/__init__.py
rogvibe/widgets/flip_card.py
rogvibe/widgets/lottery_wheel.py
rogvibe/widgets/slot_machine.py
rogvibe-0.5.0.dist-info/licenses/LICENSE
rogvibe-0.5.0.dist-info/METADATA
rogvibe-0.5.0.dist-info/WHEEL
rogvibe-0.5.0.dist-info/entry_points.txt
rogvibe-0.5.0.dist-info/top_level.txt
rogvibe-0.5.0.dist-info/RECORD
