Metadata-Version: 2.4
Name: rogvibe
Version: 0.5.0
Summary: Textual-based terminal lottery wheel.
Requires-Python: >=3.11
License-File: LICENSE
Requires-Dist: textual>=0.40
Dynamic: license-file
